gramps_ez_mcp/__init__.py
gramps_ez_mcp/cache.py
gramps_ez_mcp/server.py
gramps_ez_mcp/session.py
gramps_ez_mcp/tool_loader.py
gramps_ez_mcp/tools.py
gramps_ez_mcp/utils.py
gramps_ez_mcp-0.0.1.dist-info/licenses/LICENSE
gramps_ez_mcp-0.0.1.dist-info/METADATA
gramps_ez_mcp-0.0.1.dist-info/WHEEL
gramps_ez_mcp-0.0.1.dist-info/entry_points.txt
gramps_ez_mcp-0.0.1.dist-info/top_level.txt
gramps_ez_mcp-0.0.1.dist-info/RECORD
