Metadata-Version: 2.4
Name: gramps-ez-mcp
Version: 0.0.1
Summary: Gramps EZ MCP server
License: GPL-2.0-only
Project-URL: Homepage, https://github.com/dsblank/gramps-ez-mcp
Project-URL: Repository, https://github.com/dsblank/gramps-ez-mcp
Project-URL: Documentation, https://github.com/dsblank/gramps-ez-mcp#readme
Project-URL: Bug Tracker, https://github.com/dsblank/gramps-ez-mcp/issues
Keywords: genealogy,gramps,ml,mcp,model-context-protocol
Classifier: Development Status :: 4 - Beta
Classifier: Intended Audience :: Developers
Classifier: Intended Audience :: Science/Research
Classifier: License :: OSI Approved :: GNU General Public License v2 (GPLv2)
Classifier: Operating System :: OS Independent
Classifier: Programming Language :: Python :: 3
Classifier: Programming Language :: Python :: 3.8
Classifier: Programming Language :: Python :: 3.9
Classifier: Programming Language :: Python :: 3.10
Classifier: Programming Language :: Python :: 3.11
Classifier: Programming Language :: Python :: 3.12
Classifier: Topic :: Scientific/Engineering :: Artificial Intelligence
Classifier: Topic :: Software Development :: Libraries :: Python Modules
Requires-Python: >=3.8
License-File: LICENSE
Requires-Dist: mcp>=1.0.0
Requires-Dist: gramps
Requires-Dist: fastapi>=0.100.0
Requires-Dist: uvicorn[standard]>=0.20.0
Requires-Dist: requests>=2.25.0
Provides-Extra: dev
Requires-Dist: pytest>=7.0.0; extra == "dev"
Requires-Dist: pytest-asyncio>=0.21.0; extra == "dev"
Dynamic: license-file
